aldryn_categories/__init__.py
aldryn_categories/admin.py
aldryn_categories/apps.py
aldryn_categories/cms_wizards.py
aldryn_categories/fields.py
aldryn_categories/forms.py
aldryn_categories/models.py
aldryn_categories/locale/de/LC_MESSAGES/django.mo
aldryn_categories/locale/de/LC_MESSAGES/django.po
aldryn_categories/locale/en/LC_MESSAGES/django.mo
aldryn_categories/locale/en/LC_MESSAGES/django.po
aldryn_categories/locale/es/LC_MESSAGES/django.mo
aldryn_categories/locale/es/LC_MESSAGES/django.po
aldryn_categories/locale/fr/LC_MESSAGES/django.mo
aldryn_categories/locale/fr/LC_MESSAGES/django.po
aldryn_categories/locale/it/LC_MESSAGES/django.mo
aldryn_categories/locale/it/LC_MESSAGES/django.po
aldryn_categories/migrations/0001_initial.py
aldryn_categories/migrations/0002_auto_20150109_1415.py
aldryn_categories/migrations/0003_auto_20150128_1359.py
aldryn_categories/migrations/0004_auto_20150623_0859.py
aldryn_categories/migrations/0005_alter_category_id_alter_categorytranslation_id_and_more.py
aldryn_categories/migrations/__init__.py
aldryn_categories/tests/__init__.py
aldryn_categories/tests/base.py
aldryn_categories/tests/test_admin.py
aldryn_categories/tests/test_fields.py
aldryn_categories/tests/test_models.py
djangocms_aldryn_categories-2.0.1.dist-info/LICENSE
djangocms_aldryn_categories-2.0.1.dist-info/METADATA
djangocms_aldryn_categories-2.0.1.dist-info/WHEEL
djangocms_aldryn_categories-2.0.1.dist-info/top_level.txt
djangocms_aldryn_categories-2.0.1.dist-info/RECORD
